Metadata-Version: 2.1
Name: winney-redis
Version: 0.1.2
Summary: Object-Oriented HTTP Request
Home-page: https://github.com/olivetree123/winney-redis
Author: olivetree
Author-email: olivetree123@163.com
License: MIT
Platform: UNKNOWN
